LICENSE
LICENSE-topoSphere
MANIFEST.in
README.md
setup.py
nextbox_ui_plugin/__init__.py
nextbox_ui_plugin/admin.py
nextbox_ui_plugin/filters.py
nextbox_ui_plugin/forms.py
nextbox_ui_plugin/models.py
nextbox_ui_plugin/navigation.py
nextbox_ui_plugin/template_content.py
nextbox_ui_plugin/urls.py
nextbox_ui_plugin/views.py
nextbox_ui_plugin.egg-info/PKG-INFO
nextbox_ui_plugin.egg-info/SOURCES.txt
nextbox_ui_plugin.egg-info/dependency_links.txt
nextbox_ui_plugin.egg-info/top_level.txt
nextbox_ui_plugin/api/__init__.py
nextbox_ui_plugin/api/serializers.py
nextbox_ui_plugin/api/urls.py
nextbox_ui_plugin/api/views.py
nextbox_ui_plugin/migrations/0001_initial.py
nextbox_ui_plugin/migrations/__init__.py
nextbox_ui_plugin/static/nextbox_ui_plugin/modal.js
nextbox_ui_plugin/static/nextbox_ui_plugin/topoSphereApp.js
nextbox_ui_plugin/static/nextbox_ui_plugin/topoSphere/LICENSE-topoSphere
nextbox_ui_plugin/static/nextbox_ui_plugin/topoSphere/topoSphere.js
nextbox_ui_plugin/templates/nextbox_ui_plugin/site_topo_button_4.x.html
nextbox_ui_plugin/templates/nextbox_ui_plugin/site_topology_4.x.html
nextbox_ui_plugin/templates/nextbox_ui_plugin/topology_4.x.html