Metadata-Version: 2.1
Name: nextbox-ui-plugin
Version: 1.0.7
Summary: A Next-Gen Topology Visualization Plugin for NetBox Powered by topoSphere SDK.
Home-page: https://github.com/iDebugAll/nextbox-ui-plugin
Author: Igor Korotchenkov
Author-email: iDebugAll@gmail.com
License: MIT
Download-URL: https://github.com/iDebugAll/nextbox-ui-plugin/archive/v1.0.7.tar.gz
Keywords: netbox,netbox-plugin,plugin
Platform: UNKNOWN
Classifier: Development Status :: 4 - Beta
Classifier: Programming Language :: Python :: 3
Classifier: Programming Language :: Python :: 3.6
Classifier: Programming Language :: Python :: 3.7
Classifier: Programming Language :: Python :: 3.8
License-File: LICENSE
License-File: LICENSE-topoSphere
